omnidoc/__init__.py
omnidoc/markdown.py
omnidoc/tree.py
omnidoc/typesystem.py
omarkdown-0.0.3.dist-info/LICENSE
omarkdown-0.0.3.dist-info/METADATA
omarkdown-0.0.3.dist-info/WHEEL
omarkdown-0.0.3.dist-info/top_level.txt
omarkdown-0.0.3.dist-info/RECORD
