Metadata-Version: 2.1
Name: omarkdown
Version: 0.0.3
Summary: Markdown conversion to html using lark
Home-page: https://github.com/omnidoc/omnidoc
Author: MANITEJA
Author-email: teja3536mani@gmail.com
License: UNKNOWN
Platform: UNKNOWN
Classifier: Programming Language :: Python :: 3
Classifier: License :: OSI Approved :: MIT License
Classifier: Operating System :: OS Independent
Requires-Python: >=3.6
